cellmanager/__init__.py
cellmanager/core.py
cellmanager-0.1.2.dist-info/METADATA
cellmanager-0.1.2.dist-info/WHEEL
cellmanager-0.1.2.dist-info/RECORD
